{
  "id": "color-palette-manager",
  "category": "UI",
  "title": "Brand Color Palette Manager",
  "description": "Build UI component for selecting and managing brand colors with color picker, palette presets, and color visualization. Store selections in prompt configuration.",
  "status": "backlog",
  "priority": 1,
  "complexity": "simple",
  "dependencies": [
    "prompt-builder-ui",
    "prompt-builder-storage"
  ],
  "createdAt": "2025-12-27T10:46:03.052Z",
  "updatedAt": "2025-12-27T11:33:26.654Z",
  "branchName": "main",
  "startedAt": "2025-12-27T11:33:16.193Z"
}